[{"title":"This is my first post ever","decription":"Nothing so serious, it's just a formality","id":"036b1a76-1f2a-44f3-bfa7-b274929f00fc","userId":"41c8dae2-bb11-4cf4-8bc1-7d3bb5b870b3","createdAt":"2023-04-16T13:53:35.709Z","updatedAt":"2023-04-16T13:53:35.709Z"},{"title":"This is my second post ever","decription":"Nothing so serious, it's just a formality","id":"fa955857-bbd4-45b8-8778-91a0b996017e","userId":"41c8dae2-bb11-4cf4-8bc1-7d3bb5b870b3","createdAt":"2023-04-16T14:15:25.331Z","updatedAt":"2023-04-16T14:15:25.331Z"}]
